polyany/__init__.py
polyany/exponents.py
polyany/polynomial.py
polyany/py.typed
polyany/types.py
polyany-0.4.0.dist-info/METADATA
polyany-0.4.0.dist-info/WHEEL
polyany-0.4.0.dist-info/licenses/LICENSE
polyany-0.4.0.dist-info/RECORD
