Metadata-Version: 2.4
Name: polyany
Version: 0.4.0
Summary: A Python package for algebraic manipulation of multivariate polynomials
Project-URL: Homepage, https://rolmip.github.io/polyany/
Project-URL: Documentation, https://rolmip.github.io/polyany/
Project-URL: Repository, https://github.com/rolmip/polyany
Project-URL: Issues, https://github.com/rolmip/polyany/issues
Author-email: Cristiano Agulhari <agulhari@utfpr.edu.br>, Esdras Battosti <esdras.2019@alunos.utfpr.edu.br>
License-Expression: BSD-3-Clause
License-File: LICENSE
Keywords: algebra,multivariate,polynomials
Classifier: Development Status :: 3 - Alpha
Classifier: Operating System :: MacOS
Classifier: Operating System :: Microsoft :: Windows
Classifier: Operating System :: POSIX
Classifier: Operating System :: Unix
Classifier: Programming Language :: Python :: 3 :: Only
Classifier: Programming Language :: Python :: 3.11
Classifier: Programming Language :: Python :: 3.12
Classifier: Programming Language :: Python :: 3.13
Classifier: Programming Language :: Python :: Implementation :: CPython
Classifier: Topic :: Scientific/Engineering :: Mathematics
Requires-Python: >=3.11
Requires-Dist: numpy>=2.3.1
